pip_save
tests
